{"errors":[],"warnings":[],"namedChunkGroups":{"app":{"chunks":[4,1,0],"assets":["webpack-runtime-81d16d3bd6bb928bd4b2.js","webpack-runtime-81d16d3bd6bb928bd4b2.js.map","commons-5ca348266bf615bb4946.js","commons-5ca348266bf615bb4946.js.map","app-2277c9de46d2d00da769.js","app-2277c9de46d2d00da769.js.map"],"children":{},"childAssets":{}},"component---src-pages-index-js":{"chunks":[3,2],"assets":["styles.6ab697c9909e544ef494.css","styles-99333b5f7943a9ffcdff.js","styles-99333b5f7943a9ffcdff.js.map","component---src-pages-index-js-1f59dc887686382bda42.js","component---src-pages-index-js-1f59dc887686382bda42.js.map"],"children":{},"childAssets":{}}},"assetsByChunkName":{"app":["webpack-runtime-81d16d3bd6bb928bd4b2.js","commons-5ca348266bf615bb4946.js","app-2277c9de46d2d00da769.js"],"component---src-pages-index-js":["styles.6ab697c9909e544ef494.css","styles-99333b5f7943a9ffcdff.js","component---src-pages-index-js-1f59dc887686382bda42.js"]}}